read_test.py
write_test.py
cstruct2/__init__.py
cstruct2/cstruct2.py
cstruct2/cstruct2_exceptions.py
cstruct2/cstruct2_fields.py
cstruct2/cstruct2_utils.py
cstruct2-1.0.2b0.dist-info/LICENSE
cstruct2-1.0.2b0.dist-info/METADATA
cstruct2-1.0.2b0.dist-info/WHEEL
cstruct2-1.0.2b0.dist-info/top_level.txt
cstruct2-1.0.2b0.dist-info/RECORD
