Metadata-Version: 2.1
Name: cstruct2
Version: 1.0.2b0
Summary: A library for handling C-style packed binary structures easily.
Author-email: Emil Arner <arner@usa.com>
Classifier: Programming Language :: Python :: 3
Classifier: License :: OSI Approved :: MIT License
Classifier: Operating System :: OS Independent
Requires-Python: >=3.7
License-File: LICENSE
